{
  "namespace": "muldicat",
  "title": "MulDiCat - Multilingual dictionary of cataloguing terms and concepts",
  "description": "Multilingual dictionary of cataloguing terms and concepts namespace",
  "statistics": {
    "totalElements": 0,
    "totalConcepts": 40,
    "elementSets": 0,
    "vocabularies": 1
  },
  "elementSets": [],
  "vocabularies": [
    {
      "id": "muldicat",
      "title": "Multilingual dictionary of cataloguing terms and concepts (MulDiCat)",
      "description": "Terms for cataloguing and classification concepts, reflecting international agreements, intended to be used for authoritative translations of cataloguing standards and related documents of IFLA, the international Federation of Library Associations and Institutions.",
      "conceptCount": 40,
      "languages": [
        "Arabic",
        "Bulgarian",
        "Catalan",
        "Czech",
        "German",
        "English",
        "Spanish",
        "Finnish",
        "French",
        "Croatian",
        "Italian",
        "Japanese",
        "Korean",
        "Lithuanian",
        "Latvian",
        "Polish",
        "Portuguese",
        "Russian",
        "Slovak",
        "Slovenian",
        "Albanian",
        "Serbian",
        "Swedish",
        "Thai",
        "Vietnamese",
        "Chinese"
      ],
      "prefix": "muldicat",
      "url": "https://www.iflastandards.info/muldicat/"
    }
  ],
  "navigationStrategy": "simple"
}